PromptFileLoader/__init__.py
PromptFileLoader/loader.py
promptfileloader-1.0.2.dist-info/licenses/LICENSE
promptfileloader-1.0.2.dist-info/METADATA
promptfileloader-1.0.2.dist-info/WHEEL
promptfileloader-1.0.2.dist-info/top_level.txt
promptfileloader-1.0.2.dist-info/RECORD
