Metadata-Version: 2.4
Name: PromptFileLoader
Version: 1.0.2
Summary: A simple prompt loader supporting YAML and TXT files with caching
Home-page: https://github.com/akashhkrishh/PromptFileLoader
Author: Akashh Krishh
Author-email: akashhkrishh@gmail.com
Classifier: Programming Language :: Python :: 3
Classifier: License :: OSI Approved :: MIT License
Classifier: Operating System :: OS Independent
Requires-Python: >=3.6
License-File: LICENSE
Requires-Dist: PyYAML
Dynamic: author
Dynamic: author-email
Dynamic: classifier
Dynamic: description
Dynamic: description-content-type
Dynamic: home-page
Dynamic: license-file
Dynamic: requires-dist
Dynamic: requires-python
Dynamic: summary
